spaceray/__init__.py
spaceray/spaceray.py
spaceray/utils.py
spaceray-0.0.11.dist-info/LICENSE
spaceray-0.0.11.dist-info/METADATA
spaceray-0.0.11.dist-info/WHEEL
spaceray-0.0.11.dist-info/top_level.txt
spaceray-0.0.11.dist-info/RECORD
